Metadata-Version: 2.1
Name: startkit
Version: 1.2.0
Summary: A skeleton generator for python projects.
Home-page: https://github.com/niemingzhao/startkit
Author: Nie Mingzhao
Author-email: 1432440963@qq.com
License: MIT
Download-URL: https://github.com/niemingzhao/startkit/archive/master.zip
Keywords: skeleton project development
Platform: any
Classifier: Development Status :: 5 - Production/Stable
Classifier: License :: OSI Approved :: MIT License
Classifier: Operating System :: OS Independent
Classifier: Programming Language :: Python :: 3.6
Requires-Python: ~=3.6
